django_sqlbuilder/__init__.py
django_sqlbuilder/models.py
django_sqlbuilder/signals.py
django_sqlbuilder/tests.py
django_sqlbuilder/compilers/__init__.py
django_sqlbuilder/dialects/__init__.py
django_sqlbuilder/dialects/sqlite.py
sqlbuilder/__init__.py
sqlbuilder/django_sqlbuilder/__init__.py
sqlbuilder/mini/__init__.py
sqlbuilder/mini/parser.py
sqlbuilder/mini/tests.py
sqlbuilder/smartsql/__init__.py
sqlbuilder/smartsql/compiler.py
sqlbuilder/smartsql/constants.py
sqlbuilder/smartsql/datatypes.py
sqlbuilder/smartsql/exceptions.py
sqlbuilder/smartsql/expressions.py
sqlbuilder/smartsql/factory.py
sqlbuilder/smartsql/fields.py
sqlbuilder/smartsql/operator_registry.py
sqlbuilder/smartsql/operators.py
sqlbuilder/smartsql/pycompat.py
sqlbuilder/smartsql/queries.py
sqlbuilder/smartsql/tables.py
sqlbuilder/smartsql/utils.py
sqlbuilder/smartsql/compilers/__init__.py
sqlbuilder/smartsql/contrib/__init__.py
sqlbuilder/smartsql/contrib/evaluate.py
sqlbuilder/smartsql/contrib/tests/__init__.py
sqlbuilder/smartsql/contrib/tests/test_evaluate.py
sqlbuilder/smartsql/dialects/__init__.py
sqlbuilder/smartsql/dialects/cassandra.py
sqlbuilder/smartsql/dialects/mongodb.py
sqlbuilder/smartsql/dialects/mysql.py
sqlbuilder/smartsql/dialects/python.py
sqlbuilder/smartsql/dialects/sqlite.py
sqlbuilder/smartsql/tests/__init__.py
sqlbuilder/smartsql/tests/base.py
sqlbuilder/smartsql/tests/test_expressions.py
sqlbuilder/smartsql/tests/test_fields.py
sqlbuilder/smartsql/tests/test_legacy.py
sqlbuilder/smartsql/tests/test_queries.py
sqlbuilder/smartsql/tests/test_tables.py
sqlbuilder/smartsql/tests/test_utils.py
sqlbuilder/smartsql/tests/dialects/__init__.py
sqlbuilder/smartsql/tests/dialects/test_mongodb.py
sqlbuilder/smartsql/tests/dialects/test_python.py
sqlbuilder_reborn-0.5.4.dist-info/LICENSE
sqlbuilder_reborn-0.5.4.dist-info/METADATA
sqlbuilder_reborn-0.5.4.dist-info/WHEEL
sqlbuilder_reborn-0.5.4.dist-info/top_level.txt
sqlbuilder_reborn-0.5.4.dist-info/RECORD
