Metadata-Version: 2.1
Name: sqlbuilder-reborn
Version: 0.5.4
Summary: SmartSQL - lightweight sql builder.
Author: Contributors
Author-email: pkoszalka <pawel.kosazlka@daftcode.pl>, Ivan Zakrevsky <ivzak@yandex.ru>
License: Copyright (c) Ivan Zakrevsky and contributors.
Project-URL: Homepage, https://github.com/pkoszalkaa/sqlbuilder
Project-URL: OriginalPackage, https://github.com/emacsway/sqlbuilder
Keywords: SQL,database,query
Classifier: Development Status :: 5 - Production/Stable
Classifier: Intended Audience :: Developers
Classifier: License :: OSI Approved :: BSD License
Classifier: Operating System :: OS Independent
Classifier: Programming Language :: Python
Classifier: Programming Language :: Python :: 2
Classifier: Programming Language :: Python :: 2.7
Classifier: Programming Language :: Python :: 3
Classifier: Programming Language :: Python :: 3.2
Classifier: Programming Language :: Python :: 3.3
Classifier: Programming Language :: Python :: 3.4
Classifier: Topic :: Software Development :: Libraries :: Python Modules
Requires-Python: >=3.7
License-File: LICENSE
Provides-Extra: dev
Requires-Dist: black ; extra == 'dev'
Requires-Dist: bumpver ; extra == 'dev'
Requires-Dist: isort ; extra == 'dev'
Requires-Dist: pip-tools ; extra == 'dev'
Requires-Dist: pytest ; extra == 'dev'
